pgmq/__init__.py
pgmq/async_queue.py
pgmq/decorators.py
pgmq/messages.py
pgmq/queue.py
pgmq-1.0.2.dist-info/WHEEL
pgmq-1.0.2.dist-info/METADATA
pgmq-1.0.2.dist-info/RECORD
