Metadata-Version: 2.4
Name: pgmq
Version: 1.0.2
Summary: Python client for the PGMQ Postgres extension.
Keywords: pgmq,postgres,queue,async,messaging
Author: Adam Hendel
License-Expression: Apache-2.0
Classifier: Intended Audience :: Developers
Classifier: License :: OSI Approved :: Apache Software License
Classifier: Operating System :: OS Independent
Classifier: Programming Language :: Python :: 3
Classifier: Programming Language :: Python :: 3.9
Classifier: Programming Language :: Python :: 3.10
Classifier: Programming Language :: Python :: 3.11
Classifier: Programming Language :: Python :: 3.12
Classifier: Programming Language :: Python :: 3.13
Classifier: Programming Language :: Python :: 3.14
Classifier: Topic :: Database
Classifier: Topic :: Software Development :: Libraries :: Python Modules
Requires-Dist: orjson>=3.11.3
Requires-Dist: psycopg[binary,pool]>=3.2.10
Requires-Dist: asyncpg>=0.30.0 ; extra == 'async'
Maintainer: Adam Hendel, Ali Tavallaie
Maintainer-email: Ali Tavallaie <ali@techbend.io>
Requires-Python: >=3.9
Project-URL: Bug Tracker, https://github.com/pgmq/pgmq-py/issues
Project-URL: Changelog, https://github.com/pgmq/pgmq-py/blob/main/CHANGELOG.md
Project-URL: Documentation, https://github.com/pgmq/pgmq-py
Project-URL: Homepage, https://github.com/pgmq/pgmq
Project-URL: Repository, https://github.com/pgmq/pgmq-py
Provides-Extra: async
